<annotation>
	<folder>w4</folder>
	<filename>frame (17).jpg</filename>
	<path>/home/jc1da/Dropbox/FastSync/w4/frame (17).jpg</path>
	<source>
		<database>Unknown</database>
	</source>
	<size>
		<width>1280</width>
		<height>720</height>
		<depth>3</depth>
	</size>
	<segmented>0</segmented>
	<object>
		<name>CBS NEWS</name>
		<pose>Unspecified</pose>
		<truncated>0</truncated>
		<difficult>0</difficult>
		<bndbox>
			<xmin>345</xmin>
			<ymin>38</ymin>
			<xmax>519</xmax>
			<ymax>62</ymax>
		</bndbox>
	</object>
	<object>
		<name>C</name>
		<pose>Unspecified</pose>
		<truncated>0</truncated>
		<difficult>0</difficult>
		<bndbox>
			<xmin>690</xmin>
			<ymin>347</ymin>
			<xmax>737</xmax>
			<ymax>416</ymax>
		</bndbox>
	</object>
	<object>
		<name>U.N. AMBASSADOR NIKKI HALEY RESIGNING</name>
		<pose>Unspecified</pose>
		<truncated>0</truncated>
		<difficult>0</difficult>
		<bndbox>
			<xmin>86</xmin>
			<ymin>610</ymin>
			<xmax>975</xmax>
			<ymax>650</ymax>
		</bndbox>
	</object>
	<object>
		<name>CONFIRMS SHE'S LEAVING POST AT END OF THE YEAR</name>
		<pose>Unspecified</pose>
		<truncated>0</truncated>
		<difficult>0</difficult>
		<bndbox>
			<xmin>85</xmin>
			<ymin>657</ymin>
			<xmax>918</xmax>
			<ymax>683</ymax>
		</bndbox>
	</object>
	<object>
		<name>CBSN</name>
		<pose>Unspecified</pose>
		<truncated>0</truncated>
		<difficult>0</difficult>
		<bndbox>
			<xmin>1076</xmin>
			<ymin>623</ymin>
			<xmax>1239</xmax>
			<ymax>674</ymax>
		</bndbox>
	</object>
	<object>
		<name>cbsnews.com/michael</name>
		<pose>Unspecified</pose>
		<truncated>0</truncated>
		<difficult>0</difficult>
		<bndbox>
			<xmin>1011</xmin>
			<ymin>560</ymin>
			<xmax>1232</xmax>
			<ymax>581</ymax>
		</bndbox>
	</object>
	<object>
		<name>MICHAEL</name>
		<pose>Unspecified</pose>
		<truncated>0</truncated>
		<difficult>0</difficult>
		<bndbox>
			<xmin>1071</xmin>
			<ymin>508</ymin>
			<xmax>1208</xmax>
			<ymax>548</ymax>
		</bndbox>
	</object>
	<object>
		<name>HURRICANE</name>
		<pose>Unspecified</pose>
		<truncated>0</truncated>
		<difficult>0</difficult>
		<bndbox>
			<xmin>1073</xmin>
			<ymin>486</ymin>
			<xmax>1229</xmax>
			<ymax>509</ymax>
		</bndbox>
	</object>
	<object>
		<name>CBSN</name>
		<pose>Unspecified</pose>
		<truncated>1</truncated>
		<difficult>0</difficult>
		<bndbox>
			<xmin>1121</xmin>
			<ymin>106</ymin>
			<xmax>1280</xmax>
			<ymax>163</ymax>
		</bndbox>
	</object>
	<object>
		<name>WASHINGTON</name>
		<pose>Unspecified</pose>
		<truncated>1</truncated>
		<difficult>0</difficult>
		<bndbox>
			<xmin>1105</xmin>
			<ymin>164</ymin>
			<xmax>1280</xmax>
			<ymax>191</ymax>
		</bndbox>
	</object>
	<object>
		<name>E</name>
		<pose>Unspecified</pose>
		<truncated>0</truncated>
		<difficult>0</difficult>
		<bndbox>
			<xmin>2</xmin>
			<ymin>638</ymin>
			<xmax>20</xmax>
			<ymax>661</ymax>
		</bndbox>
	</object>
	<object>
		<name>W</name>
		<pose>Unspecified</pose>
		<truncated>0</truncated>
		<difficult>0</difficult>
		<bndbox>
			<xmin>44</xmin>
			<ymin>640</ymin>
			<xmax>63</xmax>
			<ymax>661</ymax>
		</bndbox>
	</object>
</annotation>
